nalp/__init__.py
nalp/core/__init__.py
nalp/core/corpus.py
nalp/core/dataset.py
nalp/core/encoder.py
nalp/core/model.py
nalp/corpus/__init__.py
nalp/corpus/audio.py
nalp/corpus/sentence.py
nalp/corpus/text.py
nalp/datasets/__init__.py
nalp/datasets/image.py
nalp/datasets/language_modeling.py
nalp/encoders/__init__.py
nalp/encoders/integer.py
nalp/encoders/word2vec.py
nalp/models/__init__.py
nalp/models/dcgan.py
nalp/models/gan.py
nalp/models/gsgan.py
nalp/models/maligan.py
nalp/models/relgan.py
nalp/models/seqgan.py
nalp/models/wgan.py
nalp/models/discriminators/__init__.py
nalp/models/discriminators/conv.py
nalp/models/discriminators/embedded_text.py
nalp/models/discriminators/linear.py
nalp/models/discriminators/lstm.py
nalp/models/discriminators/text.py
nalp/models/generators/__init__.py
nalp/models/generators/bi_lstm.py
nalp/models/generators/conv.py
nalp/models/generators/gru.py
nalp/models/generators/gumbel_lstm.py
nalp/models/generators/gumbel_rmc.py
nalp/models/generators/linear.py
nalp/models/generators/lstm.py
nalp/models/generators/rmc.py
nalp/models/generators/rnn.py
nalp/models/generators/stacked_rnn.py
nalp/models/layers/__init__.py
nalp/models/layers/gumbel_softmax.py
nalp/models/layers/multi_head_attention.py
nalp/models/layers/relational_memory_cell.py
nalp/utils/__init__.py
nalp/utils/constants.py
nalp/utils/loader.py
nalp/utils/logging.py
nalp/utils/preprocess.py
nalp-2.0.4.dist-info/LICENSE
nalp-2.0.4.dist-info/METADATA
nalp-2.0.4.dist-info/WHEEL
nalp-2.0.4.dist-info/top_level.txt
nalp-2.0.4.dist-info/RECORD
